{
    "UserAgent": "aws-amplify/cli",
    "Version": "0.1.0",
    "IdentityManager": {
        "Default": {}
    },
    "AppSync": {
        "Default": {
            "ApiUrl": "https://xys6mhvn4bawlnrfseag7w6evu.appsync-api.us-east-2.amazonaws.com/graphql",
            "Region": "us-east-2",
            "AuthMode": "API_KEY",
            "ApiKey": "da2-ouyottx3uvd43myxgeb54ybz2e",
            "ClientDatabasePrefix": "BestFriends_API_KEY"
        },
        "BestFriends_AWS_IAM": {
            "ApiUrl": "https://xys6mhvn4bawlnrfseag7w6evu.appsync-api.us-east-2.amazonaws.com/graphql",
            "Region": "us-east-2",
            "AuthMode": "AWS_IAM",
            "ClientDatabasePrefix": "BestFriends_AWS_IAM"
        }
    },
    "CredentialsProvider": {
        "CognitoIdentity": {
            "Default": {
                "PoolId": "us-east-2:9d5f4111-4cd8-403a-bea9-d7f665621a01",
                "Region": "us-east-2"
            }
        }
    },
    "CognitoUserPool": {
        "Default": {
            "PoolId": "us-east-2_iQ38JnB4Y",
            "AppClientId": "4tmrfjf1fslodormfncqpktsug",
            "Region": "us-east-2"
        }
    },
    "Auth": {
        "Default": {
            "authenticationFlowType": "USER_SRP_AUTH"
        }
    },
    "DynamoDBObjectMapper": {
        "Default": {
            "Region": "us-east-2"
        }
    }
}